QQMusicDecrypt.cpython-36m-x86_64-linux-gnu.so
QQMusicDecrypt-1.0.dist-info/LICENSE
QQMusicDecrypt-1.0.dist-info/METADATA
QQMusicDecrypt-1.0.dist-info/WHEEL
QQMusicDecrypt-1.0.dist-info/top_level.txt
QQMusicDecrypt-1.0.dist-info/RECORD
