Metadata-Version: 2.1
Name: QQMusicDecrypt
Version: 1.0
Summary: fastest way to covert qmc file
Home-page: https://github.com/rizhiyi/MusicDecoder/
Author: AlphaBrock
Author-email: jcciam@outlook.com
License: MIT License
Keywords: QQMusic,MusicDecoder,MusicDecrypt,MusicCovert
Platform: UNKNOWN
